{"data":{"site":{"siteMetadata":{"title":"Contemplating Imponderables"}},"markdownRemark":{"id":"a6b2fb54-23f8-5e08-9a70-0d5a964f0f51","excerpt":"We need Katex Today for rendering our equations. Sum square difference The sum of the squares of the first ten natural numbers is,\n12 + 22 + … + 102 = 385\nThe…","html":"<p>We need <a href=\"https://katex.org//\">Katex</a> Today for rendering our equations.</p>\n<h3>Sum square difference</h3>\n<blockquote>\n<p>The sum of the squares of the first ten natural numbers is,\n12 + 22 + … + 102 = 385\nThe square of the sum of the first ten natural numbers is,\n(1 + 2 + … + 10)2 = 552 = 3025\nHence the difference between the sum of the squares of the first ten natural numbers and the square of the sum is 3025 − 385 = 2640.\nFind the difference between the sum of the squares of the first one hundred natural numbers and the square of the sum.</p>\n</blockquote>\n<p>First things first for 1-10:<br/>\nSum of Squares: <code class=\"language-text\">1^2 + 2^2 + 3^2 + 4^2 + 5^2 + 6^2 + 7^2 + 8^2 + 9^2 + 10^2 = 385</code></p>\n<div class=\"gatsby-highlight\" data-language=\"javascript\"><pre class=\"language-javascript\"><code class=\"language-javascript\"><span class=\"token keyword\">function</span> <span class=\"token function\">getSumOfSquares</span><span class=\"token punctuation\">(</span><span class=\"token parameter\">n</span><span class=\"token punctuation\">)</span><span class=\"token punctuation\">{</span>\n  <span class=\"token keyword\">var</span> product <span class=\"token operator\">=</span> <span class=\"token number\">0</span><span class=\"token punctuation\">;</span>\n  <span class=\"token keyword\">for</span><span class=\"token punctuation\">(</span><span class=\"token keyword\">var</span> i<span class=\"token operator\">=</span><span class=\"token number\">0</span><span class=\"token punctuation\">;</span> i<span class=\"token operator\">&lt;=</span>n<span class=\"token punctuation\">;</span> i<span class=\"token operator\">++</span><span class=\"token punctuation\">)</span><span class=\"token punctuation\">{</span>\n    product <span class=\"token operator\">+=</span> <span class=\"token punctuation\">(</span>i<span class=\"token operator\">*</span>i<span class=\"token punctuation\">)</span><span class=\"token punctuation\">;</span>\n  <span class=\"token punctuation\">}</span>\n  <span class=\"token keyword\">return</span> product<span class=\"token punctuation\">;</span>\n<span class=\"token punctuation\">}</span></code></pre></div>\n<p>Square of Sums <code class=\"language-text\">(1 + 2 + 3 + 4 + 5 + 6 + 7 + 8 + 9 + 10)^2 = 3025</code>:</p>\n<div class=\"gatsby-highlight\" data-language=\"javascript\"><pre class=\"language-javascript\"><code class=\"language-javascript\"><span class=\"token keyword\">function</span> <span class=\"token function\">getSquareOfSum</span><span class=\"token punctuation\">(</span><span class=\"token parameter\">n</span><span class=\"token punctuation\">)</span><span class=\"token punctuation\">{</span>\n  <span class=\"token keyword\">var</span> sum <span class=\"token operator\">=</span> <span class=\"token number\">0</span><span class=\"token punctuation\">;</span>\n  <span class=\"token keyword\">for</span><span class=\"token punctuation\">(</span><span class=\"token keyword\">var</span> i<span class=\"token operator\">=</span><span class=\"token number\">0</span><span class=\"token punctuation\">;</span> i<span class=\"token operator\">&lt;=</span>n<span class=\"token punctuation\">;</span> i<span class=\"token operator\">++</span><span class=\"token punctuation\">)</span><span class=\"token punctuation\">{</span>\n    sum <span class=\"token operator\">+=</span> i<span class=\"token punctuation\">;</span>\n  <span class=\"token punctuation\">}</span>\n  <span class=\"token keyword\">return</span> <span class=\"token punctuation\">(</span>sum<span class=\"token operator\">*</span>sum<span class=\"token punctuation\">)</span><span class=\"token punctuation\">;</span>\n<span class=\"token punctuation\">}</span></code></pre></div>\n<p>The brute force is pretty simple:</p>\n<div class=\"gatsby-highlight\" data-language=\"javascript\"><pre class=\"language-javascript\"><code class=\"language-javascript\"><span class=\"token keyword\">function</span> <span class=\"token function\">getSolution</span><span class=\"token punctuation\">(</span><span class=\"token punctuation\">)</span><span class=\"token punctuation\">{</span>\n  <span class=\"token keyword\">var</span> n <span class=\"token operator\">=</span> <span class=\"token number\">100</span><span class=\"token punctuation\">;</span>\n  <span class=\"token keyword\">var</span> sumOfSquares <span class=\"token operator\">=</span> <span class=\"token function\">getSumOfSquares</span><span class=\"token punctuation\">(</span>n<span class=\"token punctuation\">)</span><span class=\"token punctuation\">;</span>\n  <span class=\"token keyword\">var</span> squareOfSums <span class=\"token operator\">=</span> <span class=\"token function\">getSquareOfSum</span><span class=\"token punctuation\">(</span>n<span class=\"token punctuation\">)</span><span class=\"token punctuation\">;</span>\n  <span class=\"token keyword\">return</span> <span class=\"token punctuation\">(</span>squareOfSums <span class=\"token operator\">-</span> sumOfSquares<span class=\"token punctuation\">)</span><span class=\"token punctuation\">;</span>\n<span class=\"token punctuation\">}</span></code></pre></div>\n<p>But that’s not why we’re here. We want to know the magic. Please Math, tell us your secrets!</p>\n<p>We have illustrations!</p>\n<style>\n  .box{\n    height: 10px;\n    width: 10px;\n    display: inline-block;\n    border: 1px solid black;\n  }\n\n  .row{\n    font-size: 0;\n    display: block;\n  }\n\n  .container:nth-child(2n) .row .box{\n    background: blue;\n  }\n\n  .box.same{\n    background: red !important;\n  }\n\n  .box.different{\n    background: purple !important;\n  }\n\n  .box.someDifferent{\n    background: green !important;\n  }\n</style>\n<div id=\"test\"></div>\n<p>We want the sum of all of those squares. Let’s say we have 3 coordinates: <code class=\"language-text\">(a, b, c)</code>.<br/>\n<code class=\"language-text\">a</code> will represent which of the larger squares we are looking at (0 for the smallest, 1 for the 2x2, 2 for the 3x3, etc).<br/>\n<code class=\"language-text\">b</code> will represent horizontal position within a larger square.<br/>\n<code class=\"language-text\">c</code> will represent vertical position within a larger square.<br/></p>\n<div id=\"test2\"></div>\n<p>There are <code class=\"language-text\">n</code> positions where <code class=\"language-text\">(a, b, c)</code> are all equal. For our n=4 0-indexed: <code class=\"language-text\">(0, 0, 0)</code>, <code class=\"language-text\">(1, 1, 1)</code>, <code class=\"language-text\">(2, 2, 2)</code> and <code class=\"language-text\">(3, 3, 3)</code>.<br/></p>\n<p><button id=\"toggleSame\">Toggle Same</button></p>\n<p>There are <span class=\"katex\"><span class=\"katex-mathml\"><math xmlns=\"http://www.w3.org/1998/Math/MathML\"><semantics><mrow><mn>2</mn><mrow><mo fence=\"true\">(</mo><mfrac linethickness=\"0px\"><mi>n</mi><mn>3</mn></mfrac><mo fence=\"true\">)</mo></mrow></mrow><annotation encoding=\"application/x-tex\">2\\binom{n}{3}</annotation></semantics></math></span><span class=\"katex-html\" aria-hidden=\"true\"><span class=\"base\"><span class=\"strut\" style=\"height:1.20001em;vertical-align:-0.35001em;\"></span><span class=\"mord\">2</span><span class=\"mord\"><span class=\"mopen delimcenter\" style=\"top:0em;\"><span class=\"delimsizing size1\">(</span></span><span class=\"mfrac\"><span class=\"vlist-t vlist-t2\"><span class=\"vlist-r\"><span class=\"vlist\" style=\"height:0.7453919999999999em;\"><span style=\"top:-2.3550000000000004em;\"><span class=\"pstrut\" style=\"height:2.7em;\"></span><span class=\"sizing reset-size6 size3 mtight\"><span class=\"mord mtight\"><span class=\"mord mtight\">3</span></span></span></span><span style=\"top:-3.144em;\"><span class=\"pstrut\" style=\"height:2.7em;\"></span><span class=\"sizing reset-size6 size3 mtight\"><span class=\"mord mtight\"><span class=\"mord mathnormal mtight\">n</span></span></span></span></span><span class=\"vlist-s\">​</span></span><span class=\"vlist-r\"><span class=\"vlist\" style=\"height:0.345em;\"><span></span></span></span></span></span><span class=\"mclose delimcenter\" style=\"top:0em;\"><span class=\"delimsizing size1\">)</span></span></span></span></span></span> triplets where all of the entries are different.<br/>\n<button id=\"toggleAllDifferent\">Toggle All Different</button></p>\n<p>There are <span class=\"katex\"><span class=\"katex-mathml\"><math xmlns=\"http://www.w3.org/1998/Math/MathML\"><semantics><mrow><mn>3</mn><mrow><mo fence=\"true\">(</mo><mfrac linethickness=\"0px\"><mi>n</mi><mn>2</mn></mfrac><mo fence=\"true\">)</mo></mrow></mrow><annotation encoding=\"application/x-tex\">3\\binom{n}{2}</annotation></semantics></math></span><span class=\"katex-html\" aria-hidden=\"true\"><span class=\"base\"><span class=\"strut\" style=\"height:1.20001em;vertical-align:-0.35001em;\"></span><span class=\"mord\">3</span><span class=\"mord\"><span class=\"mopen delimcenter\" style=\"top:0em;\"><span class=\"delimsizing size1\">(</span></span><span class=\"mfrac\"><span class=\"vlist-t vlist-t2\"><span class=\"vlist-r\"><span class=\"vlist\" style=\"height:0.7453919999999999em;\"><span style=\"top:-2.3550000000000004em;\"><span class=\"pstrut\" style=\"height:2.7em;\"></span><span class=\"sizing reset-size6 size3 mtight\"><span class=\"mord mtight\"><span class=\"mord mtight\">2</span></span></span></span><span style=\"top:-3.144em;\"><span class=\"pstrut\" style=\"height:2.7em;\"></span><span class=\"sizing reset-size6 size3 mtight\"><span class=\"mord mtight\"><span class=\"mord mathnormal mtight\">n</span></span></span></span></span><span class=\"vlist-s\">​</span></span><span class=\"vlist-r\"><span class=\"vlist\" style=\"height:0.345em;\"><span></span></span></span></span></span><span class=\"mclose delimcenter\" style=\"top:0em;\"><span class=\"delimsizing size1\">)</span></span></span></span></span></span> triplets where two entries are equal and one is different.<br/>\n<button id=\"toggleSomeDifferent\">Toggle some equal</button></p>\n<p>Using our handy dandy n-choose-k equation:</p>\n<p><span class=\"katex\"><span class=\"katex-mathml\"><math xmlns=\"http://www.w3.org/1998/Math/MathML\"><semantics><mrow><mrow><mo fence=\"true\">(</mo><mfrac linethickness=\"0px\"><mi>n</mi><mi>k</mi></mfrac><mo fence=\"true\">)</mo></mrow><mo>=</mo><mfrac><mrow><mi>n</mi><mo>⋅</mo><mo stretchy=\"false\">(</mo><mi>n</mi><mo>−</mo><mn>1</mn><mo stretchy=\"false\">)</mo><mo>⋯</mo><mo stretchy=\"false\">(</mo><mi>n</mi><mo>−</mo><mi>k</mi><mo>+</mo><mn>1</mn><mo stretchy=\"false\">)</mo></mrow><mrow><mi>k</mi><mo stretchy=\"false\">!</mo></mrow></mfrac><mo>=</mo><mfrac><mrow><mi>n</mi><mo stretchy=\"false\">!</mo></mrow><mrow><mi>k</mi><mo stretchy=\"false\">!</mo><mo stretchy=\"false\">(</mo><mi>n</mi><mo>−</mo><mi>k</mi><mo stretchy=\"false\">)</mo><mo stretchy=\"false\">!</mo></mrow></mfrac></mrow><annotation encoding=\"application/x-tex\">\\binom{n}{k} = \\frac{n\\cdot(n-1)\\cdots (n-k+1)}{k!} = \\frac{n!}{k!(n-k)!}</annotation></semantics></math></span><span class=\"katex-html\" aria-hidden=\"true\"><span class=\"base\"><span class=\"strut\" style=\"height:1.20001em;vertical-align:-0.35001em;\"></span><span class=\"mord\"><span class=\"mopen delimcenter\" style=\"top:0em;\"><span class=\"delimsizing size1\">(</span></span><span class=\"mfrac\"><span class=\"vlist-t vlist-t2\"><span class=\"vlist-r\"><span class=\"vlist\" style=\"height:0.7453919999999999em;\"><span style=\"top:-2.3550000000000004em;\"><span class=\"pstrut\" style=\"height:2.7em;\"></span><span class=\"sizing reset-size6 size3 mtight\"><span class=\"mord mtight\"><span class=\"mord mathnormal mtight\" style=\"margin-right:0.03148em;\">k</span></span></span></span><span style=\"top:-3.144em;\"><span class=\"pstrut\" style=\"height:2.7em;\"></span><span class=\"sizing reset-size6 size3 mtight\"><span class=\"mord mtight\"><span class=\"mord mathnormal mtight\">n</span></span></span></span></span><span class=\"vlist-s\">​</span></span><span class=\"vlist-r\"><span class=\"vlist\" style=\"height:0.345em;\"><span></span></span></span></span></span><span class=\"mclose delimcenter\" style=\"top:0em;\"><span class=\"delimsizing size1\">)</span></span></span><span class=\"mspace\" style=\"margin-right:0.2777777777777778em;\"></span><span class=\"mrel\">=</span><span class=\"mspace\" style=\"margin-right:0.2777777777777778em;\"></span></span><span class=\"base\"><span class=\"strut\" style=\"height:1.355em;vertical-align:-0.345em;\"></span><span class=\"mord\"><span class=\"mopen nulldelimiter\"></span><span class=\"mfrac\"><span class=\"vlist-t vlist-t2\"><span class=\"vlist-r\"><span class=\"vlist\" style=\"height:1.01em;\"><span style=\"top:-2.6550000000000002em;\"><span class=\"pstrut\" style=\"height:3em;\"></span><span class=\"sizing reset-size6 size3 mtight\"><span class=\"mord mtight\"><span class=\"mord mathnormal mtight\" style=\"margin-right:0.03148em;\">k</span><span class=\"mclose mtight\">!</span></span></span></span><span style=\"top:-3.23em;\"><span class=\"pstrut\" style=\"height:3em;\"></span><span class=\"frac-line\" style=\"border-bottom-width:0.04em;\"></span></span><span style=\"top:-3.485em;\"><span class=\"pstrut\" style=\"height:3em;\"></span><span class=\"sizing reset-size6 size3 mtight\"><span class=\"mord mtight\"><span class=\"mord mathnormal mtight\">n</span><span class=\"mbin mtight\">⋅</span><span class=\"mopen mtight\">(</span><span class=\"mord mathnormal mtight\">n</span><span class=\"mbin mtight\">−</span><span class=\"mord mtight\">1</span><span class=\"mclose mtight\">)</span><span class=\"minner mtight\">⋯</span><span class=\"mopen mtight\">(</span><span class=\"mord mathnormal mtight\">n</span><span class=\"mbin mtight\">−</span><span class=\"mord mathnormal mtight\" style=\"margin-right:0.03148em;\">k</span><span class=\"mbin mtight\">+</span><span class=\"mord mtight\">1</span><span class=\"mclose mtight\">)</span></span></span></span></span><span class=\"vlist-s\">​</span></span><span class=\"vlist-r\"><span class=\"vlist\" style=\"height:0.345em;\"><span></span></span></span></span></span><span class=\"mclose nulldelimiter\"></span></span><span class=\"mspace\" style=\"margin-right:0.2777777777777778em;\"></span><span class=\"mrel\">=</span><span class=\"mspace\" style=\"margin-right:0.2777777777777778em;\"></span></span><span class=\"base\"><span class=\"strut\" style=\"height:1.400108em;vertical-align:-0.52em;\"></span><span class=\"mord\"><span class=\"mopen nulldelimiter\"></span><span class=\"mfrac\"><span class=\"vlist-t vlist-t2\"><span class=\"vlist-r\"><span class=\"vlist\" style=\"height:0.8801079999999999em;\"><span style=\"top:-2.655em;\"><span class=\"pstrut\" style=\"height:3em;\"></span><span class=\"sizing reset-size6 size3 mtight\"><span class=\"mord mtight\"><span class=\"mord mathnormal mtight\" style=\"margin-right:0.03148em;\">k</span><span class=\"mclose mtight\">!</span><span class=\"mopen mtight\">(</span><span class=\"mord mathnormal mtight\">n</span><span class=\"mbin mtight\">−</span><span class=\"mord mathnormal mtight\" style=\"margin-right:0.03148em;\">k</span><span class=\"mclose mtight\">)</span><span class=\"mclose mtight\">!</span></span></span></span><span style=\"top:-3.23em;\"><span class=\"pstrut\" style=\"height:3em;\"></span><span class=\"frac-line\" style=\"border-bottom-width:0.04em;\"></span></span><span style=\"top:-3.394em;\"><span class=\"pstrut\" style=\"height:3em;\"></span><span class=\"sizing reset-size6 size3 mtight\"><span class=\"mord mtight\"><span class=\"mord mathnormal mtight\">n</span><span class=\"mclose mtight\">!</span></span></span></span></span><span class=\"vlist-s\">​</span></span><span class=\"vlist-r\"><span class=\"vlist\" style=\"height:0.52em;\"><span></span></span></span></span></span><span class=\"mclose nulldelimiter\"></span></span></span></span></span></p>\n<p><span class=\"katex\"><span class=\"katex-mathml\"><math xmlns=\"http://www.w3.org/1998/Math/MathML\"><semantics><mrow><mi>n</mi><mo>+</mo><mn>2</mn><mrow><mo fence=\"true\">(</mo><mfrac linethickness=\"0px\"><mi>n</mi><mn>3</mn></mfrac><mo fence=\"true\">)</mo></mrow><mo>+</mo><mn>3</mn><mrow><mo fence=\"true\">(</mo><mfrac linethickness=\"0px\"><mi>n</mi><mn>2</mn></mfrac><mo fence=\"true\">)</mo></mrow><mo>=</mo><mi>n</mi><mo>+</mo><mn>2</mn><mfrac><mrow><mi>n</mi><mo stretchy=\"false\">!</mo></mrow><mrow><mn>3</mn><mo stretchy=\"false\">!</mo><mo>∗</mo><mo stretchy=\"false\">(</mo><mi>n</mi><mo>−</mo><mn>3</mn><mo stretchy=\"false\">)</mo><mo stretchy=\"false\">!</mo></mrow></mfrac><mo>+</mo><mn>3</mn><mfrac><mrow><mi>n</mi><mo stretchy=\"false\">!</mo></mrow><mrow><mn>2</mn><mo stretchy=\"false\">!</mo><mo>∗</mo><mo stretchy=\"false\">(</mo><mi>n</mi><mo>−</mo><mn>2</mn><mo stretchy=\"false\">)</mo><mo stretchy=\"false\">!</mo></mrow></mfrac><mo>=</mo><mfrac><mrow><mi>n</mi><mo stretchy=\"false\">(</mo><mi>n</mi><mo>+</mo><mn>1</mn><mo stretchy=\"false\">)</mo><mo stretchy=\"false\">(</mo><mn>2</mn><mi>n</mi><mo>+</mo><mn>1</mn><mo stretchy=\"false\">)</mo></mrow><mn>6</mn></mfrac></mrow><annotation encoding=\"application/x-tex\">n + 2\\binom{n}{3} + 3\\binom{n}{2} = n + 2\\frac{n!}{3! * (n - 3)!} + 3\\frac{n!}{2! * (n - 2)!} = \\frac{n(n+1)(2n+1)}{6}</annotation></semantics></math></span><span class=\"katex-html\" aria-hidden=\"true\"><span class=\"base\"><span class=\"strut\" style=\"height:0.66666em;vertical-align:-0.08333em;\"></span><span class=\"mord mathnormal\">n</span><span class=\"mspace\" style=\"margin-right:0.2222222222222222em;\"></span><span class=\"mbin\">+</span><span class=\"mspace\" style=\"margin-right:0.2222222222222222em;\"></span></span><span class=\"base\"><span class=\"strut\" style=\"height:1.20001em;vertical-align:-0.35001em;\"></span><span class=\"mord\">2</span><span class=\"mord\"><span class=\"mopen delimcenter\" style=\"top:0em;\"><span class=\"delimsizing size1\">(</span></span><span class=\"mfrac\"><span class=\"vlist-t vlist-t2\"><span class=\"vlist-r\"><span class=\"vlist\" style=\"height:0.7453919999999999em;\"><span style=\"top:-2.3550000000000004em;\"><span class=\"pstrut\" style=\"height:2.7em;\"></span><span class=\"sizing reset-size6 size3 mtight\"><span class=\"mord mtight\"><span class=\"mord mtight\">3</span></span></span></span><span style=\"top:-3.144em;\"><span class=\"pstrut\" style=\"height:2.7em;\"></span><span class=\"sizing reset-size6 size3 mtight\"><span class=\"mord mtight\"><span class=\"mord mathnormal mtight\">n</span></span></span></span></span><span class=\"vlist-s\">​</span></span><span class=\"vlist-r\"><span class=\"vlist\" style=\"height:0.345em;\"><span></span></span></span></span></span><span class=\"mclose delimcenter\" style=\"top:0em;\"><span class=\"delimsizing size1\">)</span></span></span><span class=\"mspace\" style=\"margin-right:0.2222222222222222em;\"></span><span class=\"mbin\">+</span><span class=\"mspace\" style=\"margin-right:0.2222222222222222em;\"></span></span><span class=\"base\"><span class=\"strut\" style=\"height:1.20001em;vertical-align:-0.35001em;\"></span><span class=\"mord\">3</span><span class=\"mord\"><span class=\"mopen delimcenter\" style=\"top:0em;\"><span class=\"delimsizing size1\">(</span></span><span class=\"mfrac\"><span class=\"vlist-t vlist-t2\"><span class=\"vlist-r\"><span class=\"vlist\" style=\"height:0.7453919999999999em;\"><span style=\"top:-2.3550000000000004em;\"><span class=\"pstrut\" style=\"height:2.7em;\"></span><span class=\"sizing reset-size6 size3 mtight\"><span class=\"mord mtight\"><span class=\"mord mtight\">2</span></span></span></span><span style=\"top:-3.144em;\"><span class=\"pstrut\" style=\"height:2.7em;\"></span><span class=\"sizing reset-size6 size3 mtight\"><span class=\"mord mtight\"><span class=\"mord mathnormal mtight\">n</span></span></span></span></span><span class=\"vlist-s\">​</span></span><span class=\"vlist-r\"><span class=\"vlist\" style=\"height:0.345em;\"><span></span></span></span></span></span><span class=\"mclose delimcenter\" style=\"top:0em;\"><span class=\"delimsizing size1\">)</span></span></span><span class=\"mspace\" style=\"margin-right:0.2777777777777778em;\"></span><span class=\"mrel\">=</span><span class=\"mspace\" style=\"margin-right:0.2777777777777778em;\"></span></span><span class=\"base\"><span class=\"strut\" style=\"height:0.66666em;vertical-align:-0.08333em;\"></span><span class=\"mord mathnormal\">n</span><span class=\"mspace\" style=\"margin-right:0.2222222222222222em;\"></span><span class=\"mbin\">+</span><span class=\"mspace\" style=\"margin-right:0.2222222222222222em;\"></span></span><span class=\"base\"><span class=\"strut\" style=\"height:1.400108em;vertical-align:-0.52em;\"></span><span class=\"mord\">2</span><span class=\"mord\"><span class=\"mopen nulldelimiter\"></span><span class=\"mfrac\"><span class=\"vlist-t vlist-t2\"><span class=\"vlist-r\"><span class=\"vlist\" style=\"height:0.8801079999999999em;\"><span style=\"top:-2.655em;\"><span class=\"pstrut\" style=\"height:3em;\"></span><span class=\"sizing reset-size6 size3 mtight\"><span class=\"mord mtight\"><span class=\"mord mtight\">3</span><span class=\"mclose mtight\">!</span><span class=\"mbin mtight\">∗</span><span class=\"mopen mtight\">(</span><span class=\"mord mathnormal mtight\">n</span><span class=\"mbin mtight\">−</span><span class=\"mord mtight\">3</span><span class=\"mclose mtight\">)</span><span class=\"mclose mtight\">!</span></span></span></span><span style=\"top:-3.23em;\"><span class=\"pstrut\" style=\"height:3em;\"></span><span class=\"frac-line\" style=\"border-bottom-width:0.04em;\"></span></span><span style=\"top:-3.394em;\"><span class=\"pstrut\" style=\"height:3em;\"></span><span class=\"sizing reset-size6 size3 mtight\"><span class=\"mord mtight\"><span class=\"mord mathnormal mtight\">n</span><span class=\"mclose mtight\">!</span></span></span></span></span><span class=\"vlist-s\">​</span></span><span class=\"vlist-r\"><span class=\"vlist\" style=\"height:0.52em;\"><span></span></span></span></span></span><span class=\"mclose nulldelimiter\"></span></span><span class=\"mspace\" style=\"margin-right:0.2222222222222222em;\"></span><span class=\"mbin\">+</span><span class=\"mspace\" style=\"margin-right:0.2222222222222222em;\"></span></span><span class=\"base\"><span class=\"strut\" style=\"height:1.400108em;vertical-align:-0.52em;\"></span><span class=\"mord\">3</span><span class=\"mord\"><span class=\"mopen nulldelimiter\"></span><span class=\"mfrac\"><span class=\"vlist-t vlist-t2\"><span class=\"vlist-r\"><span class=\"vlist\" style=\"height:0.8801079999999999em;\"><span style=\"top:-2.655em;\"><span class=\"pstrut\" style=\"height:3em;\"></span><span class=\"sizing reset-size6 size3 mtight\"><span class=\"mord mtight\"><span class=\"mord mtight\">2</span><span class=\"mclose mtight\">!</span><span class=\"mbin mtight\">∗</span><span class=\"mopen mtight\">(</span><span class=\"mord mathnormal mtight\">n</span><span class=\"mbin mtight\">−</span><span class=\"mord mtight\">2</span><span class=\"mclose mtight\">)</span><span class=\"mclose mtight\">!</span></span></span></span><span style=\"top:-3.23em;\"><span class=\"pstrut\" style=\"height:3em;\"></span><span class=\"frac-line\" style=\"border-bottom-width:0.04em;\"></span></span><span style=\"top:-3.394em;\"><span class=\"pstrut\" style=\"height:3em;\"></span><span class=\"sizing reset-size6 size3 mtight\"><span class=\"mord mtight\"><span class=\"mord mathnormal mtight\">n</span><span class=\"mclose mtight\">!</span></span></span></span></span><span class=\"vlist-s\">​</span></span><span class=\"vlist-r\"><span class=\"vlist\" style=\"height:0.52em;\"><span></span></span></span></span></span><span class=\"mclose nulldelimiter\"></span></span><span class=\"mspace\" style=\"margin-right:0.2777777777777778em;\"></span><span class=\"mrel\">=</span><span class=\"mspace\" style=\"margin-right:0.2777777777777778em;\"></span></span><span class=\"base\"><span class=\"strut\" style=\"height:1.355em;vertical-align:-0.345em;\"></span><span class=\"mord\"><span class=\"mopen nulldelimiter\"></span><span class=\"mfrac\"><span class=\"vlist-t vlist-t2\"><span class=\"vlist-r\"><span class=\"vlist\" style=\"height:1.01em;\"><span style=\"top:-2.6550000000000002em;\"><span class=\"pstrut\" style=\"height:3em;\"></span><span class=\"sizing reset-size6 size3 mtight\"><span class=\"mord mtight\"><span class=\"mord mtight\">6</span></span></span></span><span style=\"top:-3.23em;\"><span class=\"pstrut\" style=\"height:3em;\"></span><span class=\"frac-line\" style=\"border-bottom-width:0.04em;\"></span></span><span style=\"top:-3.485em;\"><span class=\"pstrut\" style=\"height:3em;\"></span><span class=\"sizing reset-size6 size3 mtight\"><span class=\"mord mtight\"><span class=\"mord mathnormal mtight\">n</span><span class=\"mopen mtight\">(</span><span class=\"mord mathnormal mtight\">n</span><span class=\"mbin mtight\">+</span><span class=\"mord mtight\">1</span><span class=\"mclose mtight\">)</span><span class=\"mopen mtight\">(</span><span class=\"mord mtight\">2</span><span class=\"mord mathnormal mtight\">n</span><span class=\"mbin mtight\">+</span><span class=\"mord mtight\">1</span><span class=\"mclose mtight\">)</span></span></span></span></span><span class=\"vlist-s\">​</span></span><span class=\"vlist-r\"><span class=\"vlist\" style=\"height:0.345em;\"><span></span></span></span></span></span><span class=\"mclose nulldelimiter\"></span></span></span></span></span></p>\n<p>Testing that with <code class=\"language-text\">n = 10</code> we get the expected <code class=\"language-text\">385</code>. Alrighty, Sum of Squares boiled down to math.</p>\n<p>Time for the Square of Sums! Let’s start <a href=\"https://math.stackexchange.com/a/329357\">here</a>:</p>\n<span class=\"katex-display\"><span class=\"katex\"><span class=\"katex-mathml\"><math xmlns=\"http://www.w3.org/1998/Math/MathML\" display=\"block\"><semantics><mtable rowspacing=\"0.15999999999999992em\" columnalign=\"center center left\" columnspacing=\"1em\"><mtr><mtd><mstyle scriptlevel=\"0\" displaystyle=\"false\"><msup><mrow><mo fence=\"true\">(</mo><msubsup><mo>∑</mo><mrow><mi>j</mi><mo>=</mo><mn>0</mn></mrow><mrow><mi>n</mi><mo>−</mo><mn>1</mn></mrow></msubsup><msub><mi>Z</mi><mi>j</mi></msub><mo fence=\"true\">)</mo></mrow><mn>2</mn></msup></mstyle></mtd><mtd><mstyle scriptlevel=\"0\" displaystyle=\"false\"><mo lspace=\"0em\" rspace=\"0em\">=</mo></mstyle></mtd><mtd><mstyle scriptlevel=\"0\" displaystyle=\"false\"><mrow><mrow><mo fence=\"true\">(</mo><msubsup><mo>∑</mo><mrow><mi>i</mi><mo>=</mo><mn>0</mn></mrow><mrow><mi>n</mi><mo>−</mo><mn>1</mn></mrow></msubsup><msub><mi>Z</mi><mi>i</mi></msub><mo fence=\"true\">)</mo></mrow><mrow><mo fence=\"true\">(</mo><msubsup><mo>∑</mo><mrow><mi>j</mi><mo>=</mo><mn>0</mn></mrow><mrow><mi>n</mi><mo>−</mo><mn>1</mn></mrow></msubsup><msub><mi>Z</mi><mi>j</mi></msub><mo fence=\"true\">)</mo></mrow></mrow></mstyle></mtd></mtr><mtr><mtd><mstyle scriptlevel=\"0\" displaystyle=\"false\"><mrow></mrow></mstyle></mtd><mtd><mstyle scriptlevel=\"0\" displaystyle=\"false\"><mo lspace=\"0em\" rspace=\"0em\">=</mo></mstyle></mtd><mtd><mstyle scriptlevel=\"0\" displaystyle=\"false\"><mrow><msubsup><mo>∑</mo><mrow><mi>j</mi><mo>=</mo><mn>0</mn></mrow><mrow><mi>n</mi><mo>−</mo><mn>1</mn></mrow></msubsup><msub><mi>Z</mi><mi>j</mi></msub><mrow><mo fence=\"true\">(</mo><msub><mi>Z</mi><mi>j</mi></msub><mo>+</mo><munder><mo>∑</mo><mrow><mi>j</mi><mo mathvariant=\"normal\">≠</mo><mi>i</mi></mrow></munder><msub><mi>Z</mi><mi>i</mi></msub><mo fence=\"true\">)</mo></mrow></mrow></mstyle></mtd></mtr><mtr><mtd><mstyle scriptlevel=\"0\" displaystyle=\"false\"><mrow></mrow></mstyle></mtd><mtd><mstyle scriptlevel=\"0\" displaystyle=\"false\"><mo lspace=\"0em\" rspace=\"0em\">=</mo></mstyle></mtd><mtd><mstyle scriptlevel=\"0\" displaystyle=\"false\"><mrow><msubsup><mo>∑</mo><mrow><mi>j</mi><mo>=</mo><mn>0</mn></mrow><mrow><mi>n</mi><mo>−</mo><mn>1</mn></mrow></msubsup><msubsup><mi>Z</mi><mi>j</mi><mn>2</mn></msubsup><mo>+</mo><munder><mo>∑</mo><mrow><mi>j</mi><mo mathvariant=\"normal\">≠</mo><mi>i</mi></mrow></munder><msub><mi>Z</mi><mi>i</mi></msub><msub><mi>Z</mi><mi>j</mi></msub></mrow></mstyle></mtd></mtr></mtable><annotation encoding=\"application/x-tex\">\\begin{array}{ccl}\n\\left(\\sum\\limits_{j=0}^{n-1}Z_j\\right)^2&amp;=&amp;\\left(\\sum\\limits_{i=0}^{n-1}Z_i\\right)\\left(\\sum\\limits_{j=0}^{n-1}Z_j\\right)\\\\\n&amp;=&amp;\\sum\\limits_{j=0}^{n-1}Z_j\\left(Z_j+\\sum\\limits_{j\\neq i}Z_i\\right)\\\\\n&amp;=&amp;\\sum\\limits_{j=0}^{n-1}Z_j^2+\\sum\\limits_{j\\neq i}Z_iZ_j\\\\\n\\end{array}</annotation></semantics></math></span><span class=\"katex-html\" aria-hidden=\"true\"><span class=\"base\"><span class=\"strut\" style=\"height:8.843402em;vertical-align:-4.171701em;\"></span><span class=\"mord\"><span class=\"mtable\"><span class=\"arraycolsep\" style=\"width:0.5em;\"></span><span class=\"col-align-c\"><span class=\"vlist-t vlist-t2\"><span class=\"vlist-r\"><span class=\"vlist\" style=\"height:4.671701em;\"><span style=\"top:-6.671701em;\"><span class=\"pstrut\" style=\"height:3.954008em;\"></span><span class=\"mord\"><span class=\"minner\"><span class=\"minner\"><span class=\"mopen delimcenter\" style=\"top:0em;\"><span class=\"delimsizing size4\">(</span></span><span class=\"mop op-limits\"><span class=\"vlist-t vlist-t2\"><span class=\"vlist-r\"><span class=\"vlist\" style=\"height:1.5011130000000001em;\"><span style=\"top:-2.122331em;margin-left:0em;\"><span class=\"pstrut\" style=\"height:3em;\"></span><span class=\"sizing reset-size6 size3 mtight\"><span class=\"mord mtight\"><span class=\"mord mathnormal mtight\" style=\"margin-right:0.05724em;\">j</span><span class=\"mrel mtight\">=</span><span class=\"mord mtight\">0</span></span></span></span><span style=\"top:-3.0000050000000003em;\"><span class=\"pstrut\" style=\"height:3em;\"></span><span><span class=\"mop op-symbol small-op\">∑</span></span></span><span style=\"top:-3.950005em;margin-left:0em;\"><span class=\"pstrut\" style=\"height:3em;\"></span><span class=\"sizing reset-size6 size3 mtight\"><span class=\"mord mtight\"><span class=\"mord mathnormal mtight\">n</span><span class=\"mbin mtight\">−</span><span class=\"mord mtight\">1</span></span></span></span></span><span class=\"vlist-s\">​</span></span><span class=\"vlist-r\"><span class=\"vlist\" style=\"height:1.113777em;\"><span></span></span></span></span></span><span class=\"mspace\" style=\"margin-right:0.16666666666666666em;\"></span><span class=\"mord\"><span class=\"mord mathnormal\" style=\"margin-right:0.07153em;\">Z</span><span class=\"msupsub\"><span class=\"vlist-t vlist-t2\"><span class=\"vlist-r\"><span class=\"vlist\" style=\"height:0.311664em;\"><span style=\"top:-2.5500000000000003em;margin-left:-0.07153em;margin-right:0.05em;\"><span class=\"pstrut\" style=\"height:2.7em;\"></span><span class=\"sizing reset-size6 size3 mtight\"><span class=\"mord mathnormal mtight\" style=\"margin-right:0.05724em;\">j</span></span></span></span><span class=\"vlist-s\">​</span></span><span class=\"vlist-r\"><span class=\"vlist\" style=\"height:0.286108em;\"><span></span></span></span></span></span></span><span class=\"mclose delimcenter\" style=\"top:0em;\"><span class=\"delimsizing size4\">)</span></span></span><span class=\"msupsub\"><span class=\"vlist-t\"><span class=\"vlist-r\"><span class=\"vlist\" style=\"height:1.954008em;\"><span style=\"top:-4.2029000000000005em;margin-right:0.05em;\"><span class=\"pstrut\" style=\"height:2.7em;\"></span><span class=\"sizing reset-size6 size3 mtight\"><span class=\"mord mtight\">2</span></span></span></span></span></span></span></span></span></span><span style=\"top:-3.671671em;\"><span class=\"pstrut\" style=\"height:3.954008em;\"></span><span class=\"mord\"></span></span><span style=\"top:-0.9205280000000002em;\"><span class=\"pstrut\" style=\"height:3.954008em;\"></span><span class=\"mord\"></span></span></span><span class=\"vlist-s\">​</span></span><span class=\"vlist-r\"><span class=\"vlist\" style=\"height:4.171701em;\"><span></span></span></span></span></span><span class=\"arraycolsep\" style=\"width:0.5em;\"></span><span class=\"arraycolsep\" style=\"width:0.5em;\"></span><span class=\"col-align-c\"><span class=\"vlist-t vlist-t2\"><span class=\"vlist-r\"><span class=\"vlist\" style=\"height:4.671701em;\"><span style=\"top:-6.671701em;\"><span class=\"pstrut\" style=\"height:3.954008em;\"></span><span class=\"mord\"><span class=\"mrel\">=</span></span></span><span style=\"top:-3.671671em;\"><span class=\"pstrut\" style=\"height:3.954008em;\"></span><span class=\"mord\"><span class=\"mrel\">=</span></span></span><span style=\"top:-0.9205280000000002em;\"><span class=\"pstrut\" style=\"height:3.954008em;\"></span><span class=\"mord\"><span class=\"mrel\">=</span></span></span></span><span class=\"vlist-s\">​</span></span><span class=\"vlist-r\"><span class=\"vlist\" style=\"height:4.171701em;\"><span></span></span></span></span></span><span class=\"arraycolsep\" style=\"width:0.5em;\"></span><span class=\"arraycolsep\" style=\"width:0.5em;\"></span><span class=\"col-align-l\"><span class=\"vlist-t vlist-t2\"><span class=\"vlist-r\"><span class=\"vlist\" style=\"height:4.671701em;\"><span style=\"top:-6.671701em;\"><span class=\"pstrut\" style=\"height:3.954008em;\"></span><span class=\"mord\"><span class=\"minner\"><span class=\"mopen delimcenter\" style=\"top:0em;\"><span class=\"delimsizing size3\">(</span></span><span class=\"mop op-limits\"><span class=\"vlist-t vlist-t2\"><span class=\"vlist-r\"><span class=\"vlist\" style=\"height:1.5011130000000001em;\"><span style=\"top:-2.122331em;margin-left:0em;\"><span class=\"pstrut\" style=\"height:3em;\"></span><span class=\"sizing reset-size6 size3 mtight\"><span class=\"mord mtight\"><span class=\"mord mathnormal mtight\">i</span><span class=\"mrel mtight\">=</span><span class=\"mord mtight\">0</span></span></span></span><span style=\"top:-3.0000050000000003em;\"><span class=\"pstrut\" style=\"height:3em;\"></span><span><span class=\"mop op-symbol small-op\">∑</span></span></span><span style=\"top:-3.950005em;margin-left:0em;\"><span class=\"pstrut\" style=\"height:3em;\"></span><span class=\"sizing reset-size6 size3 mtight\"><span class=\"mord mtight\"><span class=\"mord mathnormal mtight\">n</span><span class=\"mbin mtight\">−</span><span class=\"mord mtight\">1</span></span></span></span></span><span class=\"vlist-s\">​</span></span><span class=\"vlist-r\"><span class=\"vlist\" style=\"height:0.9776689999999999em;\"><span></span></span></span></span></span><span class=\"mspace\" style=\"margin-right:0.16666666666666666em;\"></span><span class=\"mord\"><span class=\"mord mathnormal\" style=\"margin-right:0.07153em;\">Z</span><span class=\"msupsub\"><span class=\"vlist-t vlist-t2\"><span class=\"vlist-r\"><span class=\"vlist\" style=\"height:0.31166399999999994em;\"><span style=\"top:-2.5500000000000003em;margin-left:-0.07153em;margin-right:0.05em;\"><span class=\"pstrut\" style=\"height:2.7em;\"></span><span class=\"sizing reset-size6 size3 mtight\"><span class=\"mord mathnormal mtight\">i</span></span></span></span><span class=\"vlist-s\">​</span></span><span class=\"vlist-r\"><span class=\"vlist\" style=\"height:0.15em;\"><span></span></span></span></span></span></span><span class=\"mclose delimcenter\" style=\"top:0em;\"><span class=\"delimsizing size3\">)</span></span></span><span class=\"mspace\" style=\"margin-right:0.16666666666666666em;\"></span><span class=\"minner\"><span class=\"mopen delimcenter\" style=\"top:0em;\"><span class=\"delimsizing size4\">(</span></span><span class=\"mop op-limits\"><span class=\"vlist-t vlist-t2\"><span class=\"vlist-r\"><span class=\"vlist\" style=\"height:1.5011130000000001em;\"><span style=\"top:-2.122331em;margin-left:0em;\"><span class=\"pstrut\" style=\"height:3em;\"></span><span class=\"sizing reset-size6 size3 mtight\"><span class=\"mord mtight\"><span class=\"mord mathnormal mtight\" style=\"margin-right:0.05724em;\">j</span><span class=\"mrel mtight\">=</span><span class=\"mord mtight\">0</span></span></span></span><span style=\"top:-3.0000050000000003em;\"><span class=\"pstrut\" style=\"height:3em;\"></span><span><span class=\"mop op-symbol small-op\">∑</span></span></span><span style=\"top:-3.950005em;margin-left:0em;\"><span class=\"pstrut\" style=\"height:3em;\"></span><span class=\"sizing reset-size6 size3 mtight\"><span class=\"mord mtight\"><span class=\"mord mathnormal mtight\">n</span><span class=\"mbin mtight\">−</span><span class=\"mord mtight\">1</span></span></span></span></span><span class=\"vlist-s\">​</span></span><span class=\"vlist-r\"><span class=\"vlist\" style=\"height:1.113777em;\"><span></span></span></span></span></span><span class=\"mspace\" style=\"margin-right:0.16666666666666666em;\"></span><span class=\"mord\"><span class=\"mord mathnormal\" style=\"margin-right:0.07153em;\">Z</span><span class=\"msupsub\"><span class=\"vlist-t vlist-t2\"><span class=\"vlist-r\"><span class=\"vlist\" style=\"height:0.311664em;\"><span style=\"top:-2.5500000000000003em;margin-left:-0.07153em;margin-right:0.05em;\"><span class=\"pstrut\" style=\"height:2.7em;\"></span><span class=\"sizing reset-size6 size3 mtight\"><span class=\"mord mathnormal mtight\" style=\"margin-right:0.05724em;\">j</span></span></span></span><span class=\"vlist-s\">​</span></span><span class=\"vlist-r\"><span class=\"vlist\" style=\"height:0.286108em;\"><span></span></span></span></span></span></span><span class=\"mclose delimcenter\" style=\"top:0em;\"><span class=\"delimsizing size4\">)</span></span></span></span></span><span style=\"top:-3.671671em;\"><span class=\"pstrut\" style=\"height:3.954008em;\"></span><span class=\"mord\"><span class=\"mop op-limits\"><span class=\"vlist-t vlist-t2\"><span class=\"vlist-r\"><span class=\"vlist\" style=\"height:1.5011130000000001em;\"><span style=\"top:-2.122331em;margin-left:0em;\"><span class=\"pstrut\" style=\"height:3em;\"></span><span class=\"sizing reset-size6 size3 mtight\"><span class=\"mord mtight\"><span class=\"mord mathnormal mtight\" style=\"margin-right:0.05724em;\">j</span><span class=\"mrel mtight\">=</span><span class=\"mord mtight\">0</span></span></span></span><span style=\"top:-3.0000050000000003em;\"><span class=\"pstrut\" style=\"height:3em;\"></span><span><span class=\"mop op-symbol small-op\">∑</span></span></span><span style=\"top:-3.950005em;margin-left:0em;\"><span class=\"pstrut\" style=\"height:3em;\"></span><span class=\"sizing reset-size6 size3 mtight\"><span class=\"mord mtight\"><span class=\"mord mathnormal mtight\">n</span><span class=\"mbin mtight\">−</span><span class=\"mord mtight\">1</span></span></span></span></span><span class=\"vlist-s\">​</span></span><span class=\"vlist-r\"><span class=\"vlist\" style=\"height:1.113777em;\"><span></span></span></span></span></span><span class=\"mspace\" style=\"margin-right:0.16666666666666666em;\"></span><span class=\"mord\"><span class=\"mord mathnormal\" style=\"margin-right:0.07153em;\">Z</span><span class=\"msupsub\"><span class=\"vlist-t vlist-t2\"><span class=\"vlist-r\"><span class=\"vlist\" style=\"height:0.311664em;\"><span style=\"top:-2.5500000000000003em;margin-left:-0.07153em;margin-right:0.05em;\"><span class=\"pstrut\" style=\"height:2.7em;\"></span><span class=\"sizing reset-size6 size3 mtight\"><span class=\"mord mathnormal mtight\" style=\"margin-right:0.05724em;\">j</span></span></span></span><span class=\"vlist-s\">​</span></span><span class=\"vlist-r\"><span class=\"vlist\" style=\"height:0.286108em;\"><span></span></span></span></span></span></span><span class=\"mspace\" style=\"margin-right:0.16666666666666666em;\"></span><span class=\"minner\"><span class=\"mopen delimcenter\" style=\"top:0em;\"><span class=\"delimsizing size4\">(</span></span><span class=\"mord\"><span class=\"mord mathnormal\" style=\"margin-right:0.07153em;\">Z</span><span class=\"msupsub\"><span class=\"vlist-t vlist-t2\"><span class=\"vlist-r\"><span class=\"vlist\" style=\"height:0.311664em;\"><span style=\"top:-2.5500000000000003em;margin-left:-0.07153em;margin-right:0.05em;\"><span class=\"pstrut\" style=\"height:2.7em;\"></span><span class=\"sizing reset-size6 size3 mtight\"><span class=\"mord mathnormal mtight\" style=\"margin-right:0.05724em;\">j</span></span></span></span><span class=\"vlist-s\">​</span></span><span class=\"vlist-r\"><span class=\"vlist\" style=\"height:0.286108em;\"><span></span></span></span></span></span></span><span class=\"mspace\" style=\"margin-right:0.2222222222222222em;\"></span><span class=\"mbin\">+</span><span class=\"mspace\" style=\"margin-right:0.2222222222222222em;\"></span><span class=\"mop op-limits\"><span class=\"vlist-t vlist-t2\"><span class=\"vlist-r\"><span class=\"vlist\" style=\"height:0.7500050000000001em;\"><span style=\"top:-2.097887em;margin-left:0em;\"><span class=\"pstrut\" style=\"height:3em;\"></span><span class=\"sizing reset-size6 size3 mtight\"><span class=\"mord mtight\"><span class=\"mord mathnormal mtight\" style=\"margin-right:0.05724em;\">j</span><span class=\"mrel mtight\"><span class=\"mrel mtight\"><span class=\"mord vbox mtight\"><span class=\"thinbox mtight\"><span class=\"rlap mtight\"><span class=\"strut\" style=\"height:0.8888799999999999em;vertical-align:-0.19444em;\"></span><span class=\"inner\"><span class=\"mrel mtight\"></span></span><span class=\"fix\"></span></span></span></span></span><span class=\"mrel mtight\">=</span></span><span class=\"mord mathnormal mtight\">i</span></span></span></span><span style=\"top:-3.0000050000000003em;\"><span class=\"pstrut\" style=\"height:3em;\"></span><span><span class=\"mop op-symbol small-op\">∑</span></span></span></span><span class=\"vlist-s\">​</span></span><span class=\"vlist-r\"><span class=\"vlist\" style=\"height:1.138221em;\"><span></span></span></span></span></span><span class=\"mspace\" style=\"margin-right:0.16666666666666666em;\"></span><span class=\"mord\"><span class=\"mord mathnormal\" style=\"margin-right:0.07153em;\">Z</span><span class=\"msupsub\"><span class=\"vlist-t vlist-t2\"><span class=\"vlist-r\"><span class=\"vlist\" style=\"height:0.31166399999999994em;\"><span style=\"top:-2.5500000000000003em;margin-left:-0.07153em;margin-right:0.05em;\"><span class=\"pstrut\" style=\"height:2.7em;\"></span><span class=\"sizing reset-size6 size3 mtight\"><span class=\"mord mathnormal mtight\">i</span></span></span></span><span class=\"vlist-s\">​</span></span><span class=\"vlist-r\"><span class=\"vlist\" style=\"height:0.15em;\"><span></span></span></span></span></span></span><span class=\"mclose delimcenter\" style=\"top:0em;\"><span class=\"delimsizing size4\">)</span></span></span></span></span><span style=\"top:-0.9205280000000002em;\"><span class=\"pstrut\" style=\"height:3.954008em;\"></span><span class=\"mord\"><span class=\"mop op-limits\"><span class=\"vlist-t vlist-t2\"><span class=\"vlist-r\"><span class=\"vlist\" style=\"height:1.5011130000000001em;\"><span style=\"top:-2.122331em;margin-left:0em;\"><span class=\"pstrut\" style=\"height:3em;\"></span><span class=\"sizing reset-size6 size3 mtight\"><span class=\"mord mtight\"><span class=\"mord mathnormal mtight\" style=\"margin-right:0.05724em;\">j</span><span class=\"mrel mtight\">=</span><span class=\"mord mtight\">0</span></span></span></span><span style=\"top:-3.0000050000000003em;\"><span class=\"pstrut\" style=\"height:3em;\"></span><span><span class=\"mop op-symbol small-op\">∑</span></span></span><span style=\"top:-3.950005em;margin-left:0em;\"><span class=\"pstrut\" style=\"height:3em;\"></span><span class=\"sizing reset-size6 size3 mtight\"><span class=\"mord mtight\"><span class=\"mord mathnormal mtight\">n</span><span class=\"mbin mtight\">−</span><span class=\"mord mtight\">1</span></span></span></span></span><span class=\"vlist-s\">​</span></span><span class=\"vlist-r\"><span class=\"vlist\" style=\"height:1.113777em;\"><span></span></span></span></span></span><span class=\"mspace\" style=\"margin-right:0.16666666666666666em;\"></span><span class=\"mord\"><span class=\"mord mathnormal\" style=\"margin-right:0.07153em;\">Z</span><span class=\"msupsub\"><span class=\"vlist-t vlist-t2\"><span class=\"vlist-r\"><span class=\"vlist\" style=\"height:0.8141079999999999em;\"><span style=\"top:-2.441336em;margin-left:-0.07153em;margin-right:0.05em;\"><span class=\"pstrut\" style=\"height:2.7em;\"></span><span class=\"sizing reset-size6 size3 mtight\"><span class=\"mord mathnormal mtight\" style=\"margin-right:0.05724em;\">j</span></span></span><span style=\"top:-3.063em;margin-right:0.05em;\"><span class=\"pstrut\" style=\"height:2.7em;\"></span><span class=\"sizing reset-size6 size3 mtight\"><span class=\"mord mtight\">2</span></span></span></span><span class=\"vlist-s\">​</span></span><span class=\"vlist-r\"><span class=\"vlist\" style=\"height:0.394772em;\"><span></span></span></span></span></span></span><span class=\"mspace\" style=\"margin-right:0.2222222222222222em;\"></span><span class=\"mbin\">+</span><span class=\"mspace\" style=\"margin-right:0.2222222222222222em;\"></span><span class=\"mop op-limits\"><span class=\"vlist-t vlist-t2\"><span class=\"vlist-r\"><span class=\"vlist\" style=\"height:0.7500050000000001em;\"><span style=\"top:-2.097887em;margin-left:0em;\"><span class=\"pstrut\" style=\"height:3em;\"></span><span class=\"sizing reset-size6 size3 mtight\"><span class=\"mord mtight\"><span class=\"mord mathnormal mtight\" style=\"margin-right:0.05724em;\">j</span><span class=\"mrel mtight\"><span class=\"mrel mtight\"><span class=\"mord vbox mtight\"><span class=\"thinbox mtight\"><span class=\"rlap mtight\"><span class=\"strut\" style=\"height:0.8888799999999999em;vertical-align:-0.19444em;\"></span><span class=\"inner\"><span class=\"mrel mtight\"></span></span><span class=\"fix\"></span></span></span></span></span><span class=\"mrel mtight\">=</span></span><span class=\"mord mathnormal mtight\">i</span></span></span></span><span style=\"top:-3.0000050000000003em;\"><span class=\"pstrut\" style=\"height:3em;\"></span><span><span class=\"mop op-symbol small-op\">∑</span></span></span></span><span class=\"vlist-s\">​</span></span><span class=\"vlist-r\"><span class=\"vlist\" style=\"height:1.138221em;\"><span></span></span></span></span></span><span class=\"mspace\" style=\"margin-right:0.16666666666666666em;\"></span><span class=\"mord\"><span class=\"mord mathnormal\" style=\"margin-right:0.07153em;\">Z</span><span class=\"msupsub\"><span class=\"vlist-t vlist-t2\"><span class=\"vlist-r\"><span class=\"vlist\" style=\"height:0.31166399999999994em;\"><span style=\"top:-2.5500000000000003em;margin-left:-0.07153em;margin-right:0.05em;\"><span class=\"pstrut\" style=\"height:2.7em;\"></span><span class=\"sizing reset-size6 size3 mtight\"><span class=\"mord mathnormal mtight\">i</span></span></span></span><span class=\"vlist-s\">​</span></span><span class=\"vlist-r\"><span class=\"vlist\" style=\"height:0.15em;\"><span></span></span></span></span></span></span><span class=\"mord\"><span class=\"mord mathnormal\" style=\"margin-right:0.07153em;\">Z</span><span class=\"msupsub\"><span class=\"vlist-t vlist-t2\"><span class=\"vlist-r\"><span class=\"vlist\" style=\"height:0.311664em;\"><span style=\"top:-2.5500000000000003em;margin-left:-0.07153em;margin-right:0.05em;\"><span class=\"pstrut\" style=\"height:2.7em;\"></span><span class=\"sizing reset-size6 size3 mtight\"><span class=\"mord mathnormal mtight\" style=\"margin-right:0.05724em;\">j</span></span></span></span><span class=\"vlist-s\">​</span></span><span class=\"vlist-r\"><span class=\"vlist\" style=\"height:0.286108em;\"><span></span></span></span></span></span></span></span></span></span><span class=\"vlist-s\">​</span></span><span class=\"vlist-r\"><span class=\"vlist\" style=\"height:4.171701em;\"><span></span></span></span></span></span><span class=\"arraycolsep\" style=\"width:0.5em;\"></span></span></span></span></span></span></span>\n<p><span class=\"katex\"><span class=\"katex-mathml\"><math xmlns=\"http://www.w3.org/1998/Math/MathML\"><semantics><mrow><mo>=</mo><mfrac><mrow><msup><mi>n</mi><mn>2</mn></msup><mo stretchy=\"false\">(</mo><mi>n</mi><mo>+</mo><mn>1</mn><msup><mo stretchy=\"false\">)</mo><mn>2</mn></msup></mrow><mn>4</mn></mfrac></mrow><annotation encoding=\"application/x-tex\">=\\frac{n^2(n+1)^2}{4}</annotation></semantics></math></span><span class=\"katex-html\" aria-hidden=\"true\"><span class=\"base\"><span class=\"strut\" style=\"height:0.36687em;vertical-align:0em;\"></span><span class=\"mrel\">=</span><span class=\"mspace\" style=\"margin-right:0.2777777777777778em;\"></span></span><span class=\"base\"><span class=\"strut\" style=\"height:1.4539199999999999em;vertical-align:-0.345em;\"></span><span class=\"mord\"><span class=\"mopen nulldelimiter\"></span><span class=\"mfrac\"><span class=\"vlist-t vlist-t2\"><span class=\"vlist-r\"><span class=\"vlist\" style=\"height:1.10892em;\"><span style=\"top:-2.6550000000000002em;\"><span class=\"pstrut\" style=\"height:3em;\"></span><span class=\"sizing reset-size6 size3 mtight\"><span class=\"mord mtight\"><span class=\"mord mtight\">4</span></span></span></span><span style=\"top:-3.23em;\"><span class=\"pstrut\" style=\"height:3em;\"></span><span class=\"frac-line\" style=\"border-bottom-width:0.04em;\"></span></span><span style=\"top:-3.485em;\"><span class=\"pstrut\" style=\"height:3em;\"></span><span class=\"sizing reset-size6 size3 mtight\"><span class=\"mord mtight\"><span class=\"mord mtight\"><span class=\"mord mathnormal mtight\">n</span><span class=\"msupsub\"><span class=\"vlist-t\"><span class=\"vlist-r\"><span class=\"vlist\" style=\"height:0.8913142857142857em;\"><span style=\"top:-2.931em;margin-right:0.07142857142857144em;\"><span class=\"pstrut\" style=\"height:2.5em;\"></span><span class=\"sizing reset-size3 size1 mtight\"><span class=\"mord mtight\">2</span></span></span></span></span></span></span></span><span class=\"mopen mtight\">(</span><span class=\"mord mathnormal mtight\">n</span><span class=\"mbin mtight\">+</span><span class=\"mord mtight\">1</span><span class=\"mclose mtight\"><span class=\"mclose mtight\">)</span><span class=\"msupsub\"><span class=\"vlist-t\"><span class=\"vlist-r\"><span class=\"vlist\" style=\"height:0.8913142857142857em;\"><span style=\"top:-2.931em;margin-right:0.07142857142857144em;\"><span class=\"pstrut\" style=\"height:2.5em;\"></span><span class=\"sizing reset-size3 size1 mtight\"><span class=\"mord mtight\">2</span></span></span></span></span></span></span></span></span></span></span></span><span class=\"vlist-s\">​</span></span><span class=\"vlist-r\"><span class=\"vlist\" style=\"height:0.345em;\"><span></span></span></span></span></span><span class=\"mclose nulldelimiter\"></span></span></span></span></span></p>\n<p>So we can find the difference!</p>\n<p><span class=\"katex\"><span class=\"katex-mathml\"><math xmlns=\"http://www.w3.org/1998/Math/MathML\"><semantics><mrow><mfrac><mrow><msup><mi>n</mi><mn>2</mn></msup><mo stretchy=\"false\">(</mo><mi>n</mi><mo>+</mo><mn>1</mn><msup><mo stretchy=\"false\">)</mo><mn>2</mn></msup></mrow><mn>4</mn></mfrac><mo>−</mo><mi>n</mi><mo>+</mo><mn>2</mn><mfrac><mrow><mi>n</mi><mo stretchy=\"false\">!</mo></mrow><mrow><mn>3</mn><mo stretchy=\"false\">!</mo><mo>∗</mo><mo stretchy=\"false\">(</mo><mi>n</mi><mo>−</mo><mn>3</mn><mo stretchy=\"false\">)</mo><mo stretchy=\"false\">!</mo></mrow></mfrac><mo>+</mo><mn>3</mn><mfrac><mrow><mi>n</mi><mo stretchy=\"false\">!</mo></mrow><mrow><mn>2</mn><mo stretchy=\"false\">!</mo><mo>∗</mo><mo stretchy=\"false\">(</mo><mi>n</mi><mo>−</mo><mn>2</mn><mo stretchy=\"false\">)</mo><mo stretchy=\"false\">!</mo></mrow></mfrac><mo>=</mo><mfrac><mrow><mi>n</mi><mo stretchy=\"false\">(</mo><mn>3</mn><msup><mi>n</mi><mn>3</mn></msup><mo>+</mo><mn>2</mn><msup><mi>n</mi><mn>2</mn></msup><mo>−</mo><mn>3</mn><mi>n</mi><mo>−</mo><mn>2</mn><mo stretchy=\"false\">)</mo></mrow><mn>12</mn></mfrac></mrow><annotation encoding=\"application/x-tex\">\\frac{n^2(n+1)^2}{4} - n + 2\\frac{n!}{3! * (n - 3)!} + 3\\frac{n!}{2! * (n - 2)!} = \\frac{n(3n^3 + 2n^2 - 3n - 2)}{12}</annotation></semantics></math></span><span class=\"katex-html\" aria-hidden=\"true\"><span class=\"base\"><span class=\"strut\" style=\"height:1.4539199999999999em;vertical-align:-0.345em;\"></span><span class=\"mord\"><span class=\"mopen nulldelimiter\"></span><span class=\"mfrac\"><span class=\"vlist-t vlist-t2\"><span class=\"vlist-r\"><span class=\"vlist\" style=\"height:1.10892em;\"><span style=\"top:-2.6550000000000002em;\"><span class=\"pstrut\" style=\"height:3em;\"></span><span class=\"sizing reset-size6 size3 mtight\"><span class=\"mord mtight\"><span class=\"mord mtight\">4</span></span></span></span><span style=\"top:-3.23em;\"><span class=\"pstrut\" style=\"height:3em;\"></span><span class=\"frac-line\" style=\"border-bottom-width:0.04em;\"></span></span><span style=\"top:-3.485em;\"><span class=\"pstrut\" style=\"height:3em;\"></span><span class=\"sizing reset-size6 size3 mtight\"><span class=\"mord mtight\"><span class=\"mord mtight\"><span class=\"mord mathnormal mtight\">n</span><span class=\"msupsub\"><span class=\"vlist-t\"><span class=\"vlist-r\"><span class=\"vlist\" style=\"height:0.8913142857142857em;\"><span style=\"top:-2.931em;margin-right:0.07142857142857144em;\"><span class=\"pstrut\" style=\"height:2.5em;\"></span><span class=\"sizing reset-size3 size1 mtight\"><span class=\"mord mtight\">2</span></span></span></span></span></span></span></span><span class=\"mopen mtight\">(</span><span class=\"mord mathnormal mtight\">n</span><span class=\"mbin mtight\">+</span><span class=\"mord mtight\">1</span><span class=\"mclose mtight\"><span class=\"mclose mtight\">)</span><span class=\"msupsub\"><span class=\"vlist-t\"><span class=\"vlist-r\"><span class=\"vlist\" style=\"height:0.8913142857142857em;\"><span style=\"top:-2.931em;margin-right:0.07142857142857144em;\"><span class=\"pstrut\" style=\"height:2.5em;\"></span><span class=\"sizing reset-size3 size1 mtight\"><span class=\"mord mtight\">2</span></span></span></span></span></span></span></span></span></span></span></span><span class=\"vlist-s\">​</span></span><span class=\"vlist-r\"><span class=\"vlist\" style=\"height:0.345em;\"><span></span></span></span></span></span><span class=\"mclose nulldelimiter\"></span></span><span class=\"mspace\" style=\"margin-right:0.2222222222222222em;\"></span><span class=\"mbin\">−</span><span class=\"mspace\" style=\"margin-right:0.2222222222222222em;\"></span></span><span class=\"base\"><span class=\"strut\" style=\"height:0.66666em;vertical-align:-0.08333em;\"></span><span class=\"mord mathnormal\">n</span><span class=\"mspace\" style=\"margin-right:0.2222222222222222em;\"></span><span class=\"mbin\">+</span><span class=\"mspace\" style=\"margin-right:0.2222222222222222em;\"></span></span><span class=\"base\"><span class=\"strut\" style=\"height:1.400108em;vertical-align:-0.52em;\"></span><span class=\"mord\">2</span><span class=\"mord\"><span class=\"mopen nulldelimiter\"></span><span class=\"mfrac\"><span class=\"vlist-t vlist-t2\"><span class=\"vlist-r\"><span class=\"vlist\" style=\"height:0.8801079999999999em;\"><span style=\"top:-2.655em;\"><span class=\"pstrut\" style=\"height:3em;\"></span><span class=\"sizing reset-size6 size3 mtight\"><span class=\"mord mtight\"><span class=\"mord mtight\">3</span><span class=\"mclose mtight\">!</span><span class=\"mbin mtight\">∗</span><span class=\"mopen mtight\">(</span><span class=\"mord mathnormal mtight\">n</span><span class=\"mbin mtight\">−</span><span class=\"mord mtight\">3</span><span class=\"mclose mtight\">)</span><span class=\"mclose mtight\">!</span></span></span></span><span style=\"top:-3.23em;\"><span class=\"pstrut\" style=\"height:3em;\"></span><span class=\"frac-line\" style=\"border-bottom-width:0.04em;\"></span></span><span style=\"top:-3.394em;\"><span class=\"pstrut\" style=\"height:3em;\"></span><span class=\"sizing reset-size6 size3 mtight\"><span class=\"mord mtight\"><span class=\"mord mathnormal mtight\">n</span><span class=\"mclose mtight\">!</span></span></span></span></span><span class=\"vlist-s\">​</span></span><span class=\"vlist-r\"><span class=\"vlist\" style=\"height:0.52em;\"><span></span></span></span></span></span><span class=\"mclose nulldelimiter\"></span></span><span class=\"mspace\" style=\"margin-right:0.2222222222222222em;\"></span><span class=\"mbin\">+</span><span class=\"mspace\" style=\"margin-right:0.2222222222222222em;\"></span></span><span class=\"base\"><span class=\"strut\" style=\"height:1.400108em;vertical-align:-0.52em;\"></span><span class=\"mord\">3</span><span class=\"mord\"><span class=\"mopen nulldelimiter\"></span><span class=\"mfrac\"><span class=\"vlist-t vlist-t2\"><span class=\"vlist-r\"><span class=\"vlist\" style=\"height:0.8801079999999999em;\"><span style=\"top:-2.655em;\"><span class=\"pstrut\" style=\"height:3em;\"></span><span class=\"sizing reset-size6 size3 mtight\"><span class=\"mord mtight\"><span class=\"mord mtight\">2</span><span class=\"mclose mtight\">!</span><span class=\"mbin mtight\">∗</span><span class=\"mopen mtight\">(</span><span class=\"mord mathnormal mtight\">n</span><span class=\"mbin mtight\">−</span><span class=\"mord mtight\">2</span><span class=\"mclose mtight\">)</span><span class=\"mclose mtight\">!</span></span></span></span><span style=\"top:-3.23em;\"><span class=\"pstrut\" style=\"height:3em;\"></span><span class=\"frac-line\" style=\"border-bottom-width:0.04em;\"></span></span><span style=\"top:-3.394em;\"><span class=\"pstrut\" style=\"height:3em;\"></span><span class=\"sizing reset-size6 size3 mtight\"><span class=\"mord mtight\"><span class=\"mord mathnormal mtight\">n</span><span class=\"mclose mtight\">!</span></span></span></span></span><span class=\"vlist-s\">​</span></span><span class=\"vlist-r\"><span class=\"vlist\" style=\"height:0.52em;\"><span></span></span></span></span></span><span class=\"mclose nulldelimiter\"></span></span><span class=\"mspace\" style=\"margin-right:0.2777777777777778em;\"></span><span class=\"mrel\">=</span><span class=\"mspace\" style=\"margin-right:0.2777777777777778em;\"></span></span><span class=\"base\"><span class=\"strut\" style=\"height:1.4539199999999999em;vertical-align:-0.345em;\"></span><span class=\"mord\"><span class=\"mopen nulldelimiter\"></span><span class=\"mfrac\"><span class=\"vlist-t vlist-t2\"><span class=\"vlist-r\"><span class=\"vlist\" style=\"height:1.10892em;\"><span style=\"top:-2.6550000000000002em;\"><span class=\"pstrut\" style=\"height:3em;\"></span><span class=\"sizing reset-size6 size3 mtight\"><span class=\"mord mtight\"><span class=\"mord mtight\">1</span><span class=\"mord mtight\">2</span></span></span></span><span style=\"top:-3.23em;\"><span class=\"pstrut\" style=\"height:3em;\"></span><span class=\"frac-line\" style=\"border-bottom-width:0.04em;\"></span></span><span style=\"top:-3.485em;\"><span class=\"pstrut\" style=\"height:3em;\"></span><span class=\"sizing reset-size6 size3 mtight\"><span class=\"mord mtight\"><span class=\"mord mathnormal mtight\">n</span><span class=\"mopen mtight\">(</span><span class=\"mord mtight\">3</span><span class=\"mord mtight\"><span class=\"mord mathnormal mtight\">n</span><span class=\"msupsub\"><span class=\"vlist-t\"><span class=\"vlist-r\"><span class=\"vlist\" style=\"height:0.8913142857142857em;\"><span style=\"top:-2.931em;margin-right:0.07142857142857144em;\"><span class=\"pstrut\" style=\"height:2.5em;\"></span><span class=\"sizing reset-size3 size1 mtight\"><span class=\"mord mtight\">3</span></span></span></span></span></span></span></span><span class=\"mbin mtight\">+</span><span class=\"mord mtight\">2</span><span class=\"mord mtight\"><span class=\"mord mathnormal mtight\">n</span><span class=\"msupsub\"><span class=\"vlist-t\"><span class=\"vlist-r\"><span class=\"vlist\" style=\"height:0.8913142857142857em;\"><span style=\"top:-2.931em;margin-right:0.07142857142857144em;\"><span class=\"pstrut\" style=\"height:2.5em;\"></span><span class=\"sizing reset-size3 size1 mtight\"><span class=\"mord mtight\">2</span></span></span></span></span></span></span></span><span class=\"mbin mtight\">−</span><span class=\"mord mtight\">3</span><span class=\"mord mathnormal mtight\">n</span><span class=\"mbin mtight\">−</span><span class=\"mord mtight\">2</span><span class=\"mclose mtight\">)</span></span></span></span></span><span class=\"vlist-s\">​</span></span><span class=\"vlist-r\"><span class=\"vlist\" style=\"height:0.345em;\"><span></span></span></span></span></span><span class=\"mclose nulldelimiter\"></span></span></span></span></span></p>\n<p>There we go, one nice equation.</p>\n<script>\n  function hasClass(target, nameOfClass){\n    return (\" \" + target.className + \" \").replace(/[\\n\\t]/g, \" \").indexOf(nameOfClass) > -1;\n  }\n\n  function createSquares(n, anchor){\n    var target = document.getElementById(anchor);\n    for(var a=1; a<=n; a++){\n      var newContainer = document.createElement(\"div\");\n      newContainer.setAttribute('class', 'container');\n      target.append(newContainer);\n      for(var b=0; b<a; b++){\n        var newRow = document.createElement(\"div\");\n        newRow.setAttribute('class', 'row');\n        newContainer.append(newRow);      \n        for(var c=0; c<a; c++){\n          var newBox = document.createElement(\"div\");\n          newBox.setAttribute('class', 'box');\n          newRow.append(newBox);\n        }\n      }\n    }\n  }\n\n  function toggleSquaresSame(n, anchor){\n    var target = document.getElementById(anchor);\n    for(var a=0; a < n; a++){\n      var newContainer = target.children[a];\n      for(var b=0; b<=a; b++){\n        var newRow = newContainer.children[b];\n        for(var c=0; c<=a; c++){\n          var newBox = newRow.children[c];\n          if(a === b && a === c){\n            if(hasClass(newBox, \"same\"))\n              newBox.classList.remove('same');\n            else\n              newBox.classList.add('same');\n          }\n        }\n      }\n    }\n  }\n\n  function toggleSomeDifferent(n, anchor){\n    var target = document.getElementById(anchor);\n    for(var a=0; a < n; a++){\n      var newContainer = target.children[a];\n      for(var b=0; b<=a; b++){\n        var newRow = newContainer.children[b];\n        for(var c=0; c<=a; c++){\n          var newBox = newRow.children[c];\n          if(a === b && a !== c ||\n          b === c && b !== a ||\n          a === c && a !== b){\n            if(hasClass(newBox, \"someDifferent\"))\n              newBox.classList.remove('someDifferent');\n            else\n              newBox.classList.add('someDifferent');            \n          }\n        }\n      }\n    }\n  }\n\n  function toggleAllDifferent(n, anchor){\n    var target = document.getElementById(anchor);\n    for(var a=0; a < n; a++){\n      var newContainer = target.children[a];\n      for(var b=0; b<=a; b++){\n        var newRow = newContainer.children[b];\n        for(var c=0; c<=a; c++){\n          var newBox = newRow.children[c];\n          if(a !== b && a !== c && b !== c){\n            if(hasClass(newBox, \"different\"))\n              newBox.classList.remove('different');\n            else\n              newBox.classList.add('different');\n          }\n        }\n      }\n    }\n  }\n\n  createSquares(4, \"test\");\n  createSquares(4, \"test2\");\n  document.getElementById(\"toggleSame\").onclick = function(){\n    toggleSquaresSame(4, \"test2\");\n  }\n  document.getElementById(\"toggleSomeDifferent\").onclick = function(){\n    toggleSomeDifferent(4, \"test2\");\n  }\n\n  document.getElementById(\"toggleAllDifferent\").onclick = function(){\n    toggleAllDifferent(4, \"test2\");\n  }\n\n\n</script>","frontmatter":{"title":"Let's Solve Project Euler Problem 6","date":"June 16, 2017","description":"Euler Problem 6"}}},"pageContext":{"slug":"/project-euler-6/","previous":{"fields":{"slug":"/project-euler-5/"},"frontmatter":{"title":"Let's Solve Project Euler Problem 5"}},"next":{"fields":{"slug":"/project-euler-7/"},"frontmatter":{"title":"Let's Solve Project Euler Problem 7"}}}}